LICENSE
MANIFEST.in
setup.cfg
setup.py
gflow/GalaxyCMDWorkflow.py
gflow/__init__.py
gflow.egg-info/PKG-INFO
gflow.egg-info/SOURCES.txt
gflow.egg-info/dependency_links.txt
gflow.egg-info/top_level.txt
scripts/gflow