Metadata-Version: 1.1
Name: gflow
Version: 0.1
Summary: Command line tool for running Galaxy workflows.
Home-page: https://github.com/AAFC-MBB/gflow
Author: Alex MacLean
Author-email: maclean199@gmail.com
License: UNKNOWN
Download-URL: https://github.com/AAFC-MBB/gflow/archive/0.1.tar.gz
Keywords: Galaxy,Workflow,Python,Bioblend
Platform: UNKNOWN
